umfactory/__init__.py
umfactory/core.py
umfactory/pytest.py
umfactory-0.1.0.dev0.dist-info/DESCRIPTION.rst
umfactory-0.1.0.dev0.dist-info/METADATA
umfactory-0.1.0.dev0.dist-info/RECORD
umfactory-0.1.0.dev0.dist-info/WHEEL
umfactory-0.1.0.dev0.dist-info/entry_points.txt
umfactory-0.1.0.dev0.dist-info/metadata.json
umfactory-0.1.0.dev0.dist-info/top_level.txt
