Metadata-Version: 2.0
Name: umfactory
Version: 0.1.0.dev0
Summary: Factories for umongo
Home-page: https://github.com/noirbizarre/umfactory
Author: API Hackers
Author-email: noirbizarre+umfactory@gmail.com
License: MIT
Keywords: umongo motor factory mongo pytest
Platform: UNKNOWN
Classifier: Development Status :: 3 - Alpha
Classifier: Programming Language :: Python
Classifier: Environment :: Web Environment
Classifier: Operating System :: OS Independent
Classifier: Intended Audience :: Developers
Classifier: Topic :: System :: Software Distribution
Classifier: Programming Language :: Python
Classifier: Programming Language :: Python :: 3
Classifier: Programming Language :: Python :: 3.6
Classifier: Topic :: Software Development :: Libraries :: Python Modules
Classifier: License :: OSI Approved :: MIT License
Requires-Dist: Faker (>=0.8.0)
Requires-Dist: umongo (>=0.15.0)
Provides-Extra: test
Requires-Dist: motor (==1.2.0); extra == 'test'
Requires-Dist: pytest (==3.3.1); extra == 'test'
Requires-Dist: pytest-asyncio (==0.8.0); extra == 'test'
Requires-Dist: pytest-faker (==2.0.0); extra == 'test'
Requires-Dist: pytest-sugar (==0.9.0); extra == 'test'
